etuples/__init__.py
etuples/_version.py
etuples/core.py
etuples/dispatch.py
etuples-0.3.2.dist-info/LICENSE
etuples-0.3.2.dist-info/METADATA
etuples-0.3.2.dist-info/WHEEL
etuples-0.3.2.dist-info/top_level.txt
etuples-0.3.2.dist-info/RECORD
